active_erroring/__init__.py
active_erroring/main.py
Active_Erroring-1.1.2.dist-info/METADATA
Active_Erroring-1.1.2.dist-info/WHEEL
Active_Erroring-1.1.2.dist-info/top_level.txt
Active_Erroring-1.1.2.dist-info/RECORD
