Metadata-Version: 2.1
Name: Active-Erroring
Version: 1.1.2
Summary: This package can be used to raise custom errors and have fun.
Home-page: https://github.com/Armen-Jean-Andreasian/Active-Erroring
Author: Armen-Jean Andreasian
Author-email: armen.andreasian77@gmail.com
License: MIT
Keywords: error,raising,custom,python
Classifier: Development Status :: 3 - Alpha
Classifier: Intended Audience :: Developers
Classifier: Topic :: Software Development :: Build Tools
Classifier: License :: OSI Approved :: MIT License
Classifier: Programming Language :: Python :: 3.8
Classifier: Programming Language :: Python :: 3.9
Classifier: Programming Language :: Python :: 3.10
Classifier: Programming Language :: Python :: 3.11
